MANIFEST.in
README
setup.py
gae_command/__init__.py
gae_command/command.py
gae_command/config.py
gae_command/gae_command.conf
gae_command/stub_setup.py
gae_command/template.py
gae_command/version.py
gae_command.egg-info/PKG-INFO
gae_command.egg-info/SOURCES.txt
gae_command.egg-info/dependency_links.txt
gae_command.egg-info/entry_points.txt
gae_command.egg-info/requires.txt
gae_command.egg-info/top_level.txt
tests/__init__.py