Metadata-Version: 1.1
Name: gae-command
Version: 0.2.8
Summary: A tool to download and invoke gae commands.
Home-page: http://packages.python.org/gae_command
Author: Alex Bodnaru
Author-email: alexbodn@gmail.com
License: BSD
Keywords: gae
Platform: UNKNOWN
Classifier: Development Status :: 3 - Alpha
Classifier: Topic :: Utilities
Classifier: Environment :: Console
Classifier: License :: OSI Approved :: BSD License
